hyo2.bag-1.2.12-py3.11-nspkg.pth
hyo2/bag/__init__.py
hyo2/bag/bag.py
hyo2/bag/base.py
hyo2/bag/bbox.py
hyo2/bag/density.py
hyo2/bag/elevation.py
hyo2/bag/helper.py
hyo2/bag/meta.py
hyo2/bag/tracklist.py
hyo2/bag/uncertainty.py
hyo2/bag/iso19139/bag/bag.xsd
hyo2/bag/iso19139/bag/bagCodelists.xml
hyo2/bag/iso19139/bag/extension.xsd
hyo2/bag/iso19139/gco/basicTypes.xsd
hyo2/bag/iso19139/gco/gco.xsd
hyo2/bag/iso19139/gco/gcoBase.xsd
hyo2/bag/iso19139/gco/readme.txt
hyo2/bag/iso19139/gmd/applicationSchema.xsd
hyo2/bag/iso19139/gmd/citation.xsd
hyo2/bag/iso19139/gmd/constraints.xsd
hyo2/bag/iso19139/gmd/content.xsd
hyo2/bag/iso19139/gmd/dataQuality.xsd
hyo2/bag/iso19139/gmd/distribution.xsd
hyo2/bag/iso19139/gmd/extent.xsd
hyo2/bag/iso19139/gmd/freeText.xsd
hyo2/bag/iso19139/gmd/gmd.xsd
hyo2/bag/iso19139/gmd/identification.xsd
hyo2/bag/iso19139/gmd/maintenance.xsd
hyo2/bag/iso19139/gmd/metadataApplication.xsd
hyo2/bag/iso19139/gmd/metadataEntity.xsd
hyo2/bag/iso19139/gmd/metadataExtension.xsd
hyo2/bag/iso19139/gmd/portrayalCatalogue.xsd
hyo2/bag/iso19139/gmd/readme.txt
hyo2/bag/iso19139/gmd/referenceSystem.xsd
hyo2/bag/iso19139/gmd/spatialRepresentation.xsd
hyo2/bag/iso19139/gmi/acquisitionInformation.xsd
hyo2/bag/iso19139/gmi/contentInformation.xsd
hyo2/bag/iso19139/gmi/dataQualityInformation.xsd
hyo2/bag/iso19139/gmi/gmi.xsd
hyo2/bag/iso19139/gmi/metadataEntitySet.xsd
hyo2/bag/iso19139/gmi/spatialRepresentationInformation.xsd
hyo2/bag/iso19139/gml/basicTypes.xsd
hyo2/bag/iso19139/gml/coordinateOperations.xsd
hyo2/bag/iso19139/gml/coordinateReferenceSystems.xsd
hyo2/bag/iso19139/gml/coordinateSystems.xsd
hyo2/bag/iso19139/gml/coverage.xsd
hyo2/bag/iso19139/gml/datums.xsd
hyo2/bag/iso19139/gml/defaultStyle.xsd
hyo2/bag/iso19139/gml/deprecatedTypes.xsd
hyo2/bag/iso19139/gml/dictionary.xsd
hyo2/bag/iso19139/gml/direction.xsd
hyo2/bag/iso19139/gml/dynamicFeature.xsd
hyo2/bag/iso19139/gml/feature.xsd
hyo2/bag/iso19139/gml/geometryAggregates.xsd
hyo2_bag-1.2.12.dist-info/AUTHORS.rst
hyo2_bag-1.2.12.dist-info/LICENSE
hyo2_bag-1.2.12.dist-info/METADATA
hyo2_bag-1.2.12.dist-info/WHEEL
hyo2_bag-1.2.12.dist-info/entry_points.txt
hyo2_bag-1.2.12.dist-info/namespace_packages.txt
hyo2_bag-1.2.12.dist-info/top_level.txt
hyo2_bag-1.2.12.dist-info/RECORD
